split_datalawyer/__init__.py
split_datalawyer/modules/__init__.py
split_datalawyer/modules/force_drop_duplicated_module.py
split_datalawyer/modules/modules_types.py
split_datalawyer/modules/replace_concatenated_dot_module.py
split_datalawyer/modules/replace_long_words_module.py
split_datalawyer/modules/replace_module.py
split_datalawyer/modules/replace_underscore_sequence_module.py
split_datalawyer/sentences/__init__.py
split_datalawyer/sentences/base_sentence_split.py
split_datalawyer/sentences/pdf_sentence_split.py
split_datalawyer/sentences/sentence_split.py
split_datalawyer/sentences/split_utils.py
split_datalawyer/tests/__init__.py
split_datalawyer/tests/test_split_sentence.py
split_datalawyer/tests/test_split_sentence_file.py
split_datalawyer/utils/__init__.py
split_datalawyer/utils/abbreviations.csv
split_datalawyer/utils/continuation_terms.csv
split_datalawyer/utils/file_utils.py
split_datalawyer/utils/hyphen_utils.py
split_datalawyer/utils/pdf_utils.py
split_datalawyer/utils/regex_utils.py
split_datalawyer/utils/stoppatterns.txt
split_datalawyer/utils/utils.py
split_datalawyer-0.1.100.dist-info/METADATA
split_datalawyer-0.1.100.dist-info/WHEEL
split_datalawyer-0.1.100.dist-info/top_level.txt
split_datalawyer-0.1.100.dist-info/zip-safe
split_datalawyer-0.1.100.dist-info/RECORD
