Metadata-Version: 2.4
Name: split-datalawyer
Version: 0.1.100
Author: Datalawyer
Requires-Dist: pandas
Requires-Dist: nltk
Requires-Dist: boto3
Requires-Dist: filelock
Requires-Dist: requests
Requires-Dist: pymupdf
Dynamic: author
Dynamic: requires-dist
